cmcccloudsdkkms/__init__.py
cmcccloudsdkkms/v2/__init__.py
cmcccloudsdkkms/v2/kms_async_client.py
cmcccloudsdkkms/v2/kms_client.py
cmcccloudsdkkms/v2/model/__init__.py
cmcccloudsdkkms/v2/model/action_resources.py
cmcccloudsdkkms/v2/model/api_link.py
cmcccloudsdkkms/v2/model/api_version_detail.py
cmcccloudsdkkms/v2/model/batch_create_kms_tags_request.py
cmcccloudsdkkms/v2/model/batch_create_kms_tags_request_body.py
cmcccloudsdkkms/v2/model/batch_create_kms_tags_response.py
cmcccloudsdkkms/v2/model/cancel_grant_request.py
cmcccloudsdkkms/v2/model/cancel_grant_response.py
cmcccloudsdkkms/v2/model/cancel_key_deletion_request.py
cmcccloudsdkkms/v2/model/cancel_key_deletion_response.py
cmcccloudsdkkms/v2/model/cancel_self_grant_request.py
cmcccloudsdkkms/v2/model/cancel_self_grant_response.py
cmcccloudsdkkms/v2/model/create_datakey_request.py
cmcccloudsdkkms/v2/model/create_datakey_request_body.py
cmcccloudsdkkms/v2/model/create_datakey_response.py
cmcccloudsdkkms/v2/model/create_datakey_without_plaintext_request.py
cmcccloudsdkkms/v2/model/create_datakey_without_plaintext_response.py
cmcccloudsdkkms/v2/model/create_grant_request.py
cmcccloudsdkkms/v2/model/create_grant_request_body.py
cmcccloudsdkkms/v2/model/create_grant_response.py
cmcccloudsdkkms/v2/model/create_key_request.py
cmcccloudsdkkms/v2/model/create_key_request_body.py
cmcccloudsdkkms/v2/model/create_key_response.py
cmcccloudsdkkms/v2/model/create_key_store_request.py
cmcccloudsdkkms/v2/model/create_key_store_request_body.py
cmcccloudsdkkms/v2/model/create_key_store_response.py
cmcccloudsdkkms/v2/model/create_kms_tag_request.py
cmcccloudsdkkms/v2/model/create_kms_tag_request_body.py
cmcccloudsdkkms/v2/model/create_kms_tag_response.py
cmcccloudsdkkms/v2/model/create_parameters_for_import_request.py
cmcccloudsdkkms/v2/model/create_parameters_for_import_response.py
cmcccloudsdkkms/v2/model/create_random_request.py
cmcccloudsdkkms/v2/model/create_random_response.py
cmcccloudsdkkms-0.0.1b0.dist-info/LICENSE
cmcccloudsdkkms-0.0.1b0.dist-info/METADATA
cmcccloudsdkkms-0.0.1b0.dist-info/WHEEL
cmcccloudsdkkms-0.0.1b0.dist-info/top_level.txt
cmcccloudsdkkms-0.0.1b0.dist-info/RECORD
