Metadata-Version: 2.1
Name: cmcccloudsdkkms
Version: 0.0.1b0
Summary: KMS
Home-page: https://github.com/cmcccloud/cmcccloud-sdk-python-v3
Author: CmccCloud SDK
Author-email: cmcccloud.sdk@gmail.com
License: Apache LICENSE 2.0
Keywords: cmcccloud,sdk,KMS
Classifier: Development Status :: 5 - Production/Stable
Classifier: Intended Audience :: Developers
Classifier: License :: OSI Approved :: Apache Software License
Classifier: Programming Language :: Python :: 2.7
Classifier: Programming Language :: Python :: 3.3
Classifier: Programming Language :: Python :: 3.4
Classifier: Programming Language :: Python :: 3.5
Classifier: Programming Language :: Python :: 3.6
Classifier: Programming Language :: Python :: 3.7
Classifier: Programming Language :: Python :: 3.8
Classifier: Programming Language :: Python :: 3.9
Classifier: Topic :: Software Development
Requires-Python: >=2.7,!=3.0.*,!=3.1.*,!=3.2.*
License-File: LICENSE
Requires-Dist: cmcccloudsdkcore >=0.0.1-beta
